LICENSE
MANIFEST.in
README.md
setup.py
calculator/__init__.py
calculator/controllers.py
calculator/models.py
calculator/views.py
easy_tui/__init__.py
easy_tui/controls.py
easy_tui.egg-info/PKG-INFO
easy_tui.egg-info/SOURCES.txt
easy_tui.egg-info/dependency_links.txt
easy_tui.egg-info/requires.txt
easy_tui.egg-info/top_level.txt
tests/__init__.py
tests/example01.py
tests/test_models.py