Metadata-Version: 2.1
Name: easy_tui
Version: 0.1.1
Summary: A miniTUI with the ability to handle simple keyboard events in a terminal.
Home-page: https://github.com/digestiveThinking/simple_screen
Author: Mon Maldonado
Author-email: monterdi@gmail.com
Classifier: Programming Language :: Python :: 3
Classifier: License :: OSI Approved :: MIT License
Classifier: Operating System :: OS Independent
Requires-Python: >=3.6
License-File: LICENSE
Requires-Dist: simple_screen==0.1.13
